ascom_mcp/__init__.py
ascom_mcp/__main__.py
ascom_mcp/ascom_logging.py
ascom_mcp/config.py
ascom_mcp/constants.py
ascom_mcp/server_fastmcp.py
ascom_mcp/devices/__init__.py
ascom_mcp/devices/device_resolver.py
ascom_mcp/devices/manager.py
ascom_mcp/devices/seestar_event_bridge.py
ascom_mcp/devices/seestar_event_handler.py
ascom_mcp/devices/state_persistence.py
ascom_mcp/resources/__init__.py
ascom_mcp/resources/event_stream.py
ascom_mcp/tools/__init__.py
ascom_mcp/tools/base.py
ascom_mcp/tools/camera.py
ascom_mcp/tools/discovery.py
ascom_mcp/tools/events.py
ascom_mcp/tools/telescope.py
ascom_mcp/utils/__init__.py
ascom_mcp/utils/errors.py
mcp_server_ascom-0.4.0.dist-info/licenses/LICENSE
mcp_server_ascom-0.4.0.dist-info/METADATA
mcp_server_ascom-0.4.0.dist-info/WHEEL
mcp_server_ascom-0.4.0.dist-info/entry_points.txt
mcp_server_ascom-0.4.0.dist-info/top_level.txt
mcp_server_ascom-0.4.0.dist-info/RECORD
