Metadata-Version: 2.4
Name: mcp-server-ascom
Version: 0.4.0
Summary: MCP server for ASCOM astronomy equipment control
Author: Stellarpunk Collective
License-Expression: MIT
Project-URL: Homepage, https://github.com/stellarpunk/mcp-server-ascom
Project-URL: Bug Tracker, https://github.com/stellarpunk/mcp-server-ascom/issues
Project-URL: Repository, https://github.com/stellarpunk/mcp-server-ascom
Project-URL: Organization, https://github.com/stellarpunk
Keywords: mcp,ascom,astronomy,telescope,alpaca,stellarpunk
Classifier: Development Status :: 3 - Alpha
Classifier: Intended Audience :: Developers
Classifier: Intended Audience :: Science/Research
Classifier: Programming Language :: Python :: 3
Classifier: Programming Language :: Python :: 3.10
Classifier: Programming Language :: Python :: 3.11
Classifier: Programming Language :: Python :: 3.12
Classifier: Topic :: Scientific/Engineering :: Astronomy
Requires-Python: >=3.10
License-File: LICENSE
Requires-Dist: fastmcp>=2.10.0
Requires-Dist: alpyca>=2.0.0
Requires-Dist: astropy>=6.0.0
Requires-Dist: aiohttp>=3.9.0
Requires-Dist: pydantic>=2.0.0
Requires-Dist: tenacity>=8.2.0
Requires-Dist: structlog>=23.0.0
Provides-Extra: dev
Requires-Dist: pytest>=7.0.0; extra == "dev"
Requires-Dist: pytest-asyncio>=0.21.0; extra == "dev"
Requires-Dist: pytest-cov>=4.0.0; extra == "dev"
Requires-Dist: black>=23.0.0; extra == "dev"
Requires-Dist: ruff>=0.1.0; extra == "dev"
Requires-Dist: mypy>=1.0.0; extra == "dev"
Dynamic: license-file
